README.md
setup.py
DashBoardUtils_DataScience.egg-info/PKG-INFO
DashBoardUtils_DataScience.egg-info/SOURCES.txt
DashBoardUtils_DataScience.egg-info/dependency_links.txt
DashBoardUtils_DataScience.egg-info/requires.txt
DashBoardUtils_DataScience.egg-info/top_level.txt
package/DashBoardsTemplates.py
package/__init__.py
package/dashboardutil.py
package/dataclassifier.py
package/formatcalculator.py
package/keyborddata.py
package/variationcalculator.py
tests/__init__.py
tests/test_formatcalculater.py