Metadata-Version: 2.1
Name: DashBoardUtils-DataScience
Version: 1.47
Summary: AutoMated visualization Features Extraction For Data Scientists and data format calculater for application developers
Home-page: UNKNOWN
Author: Rajat Mishra
Author-email: rajatsmishra@aol.com
License: UNKNOWN
Platform: UNKNOWN
Classifier: Programming Language :: Python :: 3
Classifier: License :: OSI Approved :: MIT License
Classifier: Operating System :: OS Independent
Requires-Python: >=3.6
